<?xml version="1.0" encoding="UTF-8"?>
<trees>
    <tree path="/distributed-session/pom.xml" title="模块session"/>
    <tree path="/distributed-session/session-01" title="传统session"/>
    <tree path="/distributed-session/session-02" title="redis+spring_session"/>
    <tree path="/distributed-session/session-03" title="redis+token" extension="" presentableText="" tooltipTitle=""
          icon="" textColor="" backgroundColor=""/>
    <tree path="/distributed-session/session-04" title="jwt"/>
    <tree path="/distributed-session/session-05" title="token统一处理"/>
    <tree path="/distributed-job" title="3.分布式任务调度"/>
    <tree path="/distributed-session" title="2.分布式Session"/>
    <tree path="/distributed-id-master" title="1.分布式ID"/>
    <tree path="/distributed-limiter" title="4.分布式限流"/>
    <tree path="/distributed-limiter/sentinal_limi_rule.bat" title="为模块06以后测试用"/>
    <tree path="/distributed-sharding" title="5.分库分表"/>
    <tree path="/distributed-seata" title="6.分布式事务"/>
    <tree path="/distributed-lock" title="7.分布式锁"/>
    <tree path="/distributed-job/job-01" title="直接启动,什么都不需要做"/>
    <tree path="/distributed-job/job-02" title="直接启动,什么都不做"/>
    <tree path="/distributed-job/job-03" title="直接启动,看日志"/>
    <tree path="/distributed-job/job-04" title="直接启动,看日志"/>
    <tree path="/distributed-job/job-05" title="直接启动,看日志"/>
    <tree path="/distributed-job/job-06" title="先启动xxl-job-master,在启动"/>
</trees>
